django_site_notifications-1.0.0.dist-info/DESCRIPTION.rst
django_site_notifications-1.0.0.dist-info/METADATA
django_site_notifications-1.0.0.dist-info/metadata.json
django_site_notifications-1.0.0.dist-info/RECORD
django_site_notifications-1.0.0.dist-info/top_level.txt
django_site_notifications-1.0.0.dist-info/WHEEL
site_notifications/__init__.py
site_notifications/admin.py
site_notifications/defaults.py
site_notifications/managers.py
site_notifications/middleware.py
site_notifications/models.py
site_notifications/migrations/0001_initial.py
site_notifications/migrations/__init__.py
site_notifications/south_migrations/0001_initial.py
site_notifications/south_migrations/0002_auto__add_field_notification_status.py
site_notifications/south_migrations/__init__.py
site_notifications/tests/__init__.py
site_notifications/tests/factories.py
site_notifications/tests/test_models.py
site_notifications/tests/test_smoke.py
